gtecble/__init__.py
gtecble/__version__.py
gtecble/gtecble.py
gtecble/lib/__init__.py
gtecble/lib/gtecble_lib.cpython-311-darwin.so
gtecble/lib/native/mac/universal/libgtecble.dylib
gtecble-1.24.3.dist-info/LICENSE
gtecble-1.24.3.dist-info/METADATA
gtecble-1.24.3.dist-info/WHEEL
gtecble-1.24.3.dist-info/top_level.txt
gtecble-1.24.3.dist-info/RECORD
