Metadata-Version: 2.2
Name: gtecble
Version: 1.24.3
Summary: A Bluetooth Low Energy (BLE) API. To be used only as part of g.Pype.
Home-page: https://www.gtec.at
Author: g.tec medical engineering GmbH
Author-email: support@gtec.at
License: g.tec Non-Commercial License (GNCL)
Classifier: Development Status :: 4 - Beta
Classifier: License :: Other/Proprietary License
Classifier: Operating System :: OS Independent
Classifier: Programming Language :: Python :: 3
License-File: LICENSE
Requires-Dist: numpy>=1.14.4
Dynamic: author
Dynamic: author-email
Dynamic: classifier
Dynamic: description-content-type
Dynamic: home-page
Dynamic: license
Dynamic: requires-dist
Dynamic: summary
